deftools/__init__.py
deftools-1.0.2.dist-info/LICENSE.txt
deftools-1.0.2.dist-info/METADATA
deftools-1.0.2.dist-info/WHEEL
deftools-1.0.2.dist-info/top_level.txt
deftools-1.0.2.dist-info/RECORD
