Metadata-Version: 2.1
Name: deftools
Version: 1.0.2
Summary: Python Tools
Home-page: https://github.com/haohoangofficial/deftools
Download-URL: https://github.com/haohoangofficial/deftools/tarball/1.0.2
Author: Hao Hoang
Author-email: haohoangofficial@gmail.com
License: LICENSE.txt
License-File: LICENSE.txt
